pgse/__init__.py
pgse/cli.py
pgse/algos/__init__.py
pgse/algos/aho_corasick_base.py
pgse/algos/aho_corasick_c.py
pgse/algos/aho_corasick_py.py
pgse/algos/utils.py
pgse/c_lib/aho_corasick.dll
pgse/c_lib/aho_corasick.dylib
pgse/c_lib/aho_corasick.so
pgse/dataset/__init__.py
pgse/dataset/file_label.py
pgse/dataset/loader.py
pgse/dataset/loader_inference.py
pgse/environment/__init__.py
pgse/environment/args.py
pgse/environment/ray_env.py
pgse/etc/__init__.py
pgse/etc/config.py
pgse/genome/__init__.py
pgse/genome/cache.py
pgse/genome/kmer.py
pgse/genome/sequence.py
pgse/genome/sequence_manager.py
pgse/genome/utils.py
pgse/log/__init__.py
pgse/log/logger.py
pgse/model/__init__.py
pgse/model/model_trainer.py
pgse/model/util.py
pgse/model/xgb.py
pgse/pipeline/__init__.py
pgse/pipeline/pgse_inference_pipeline.py
pgse/pipeline/pgse_inference_pipeline_web.py
pgse/pipeline/pgse_pipeline.py
pgse/pipeline/progress_manager.py
pgse/pipeline/regular_pipline.py
pgse/segment/__init__.py
pgse/segment/extender.py
pgse/segment/segment_pool.py
pgse/segment/util.py
pgse-0.8.5.dist-info/licenses/LICENSE.md
pgse-0.8.5.dist-info/METADATA
pgse-0.8.5.dist-info/WHEEL
pgse-0.8.5.dist-info/entry_points.txt
pgse-0.8.5.dist-info/top_level.txt
pgse-0.8.5.dist-info/RECORD
