Metadata-Version: 2.4
Name: pgse
Version: 0.8.5
Summary: Progressive Genome Segment Enhancement (PGSE)
Home-page: https://github.com/yinzheng-zhong/pgse
Author: Yinzheng Zhong
Author-email: yinzheng.zhong@liverpool.ac.uk
License: PolyForm Noncommercial License 1.0.0
Classifier: Programming Language :: Python :: 3
Classifier: Operating System :: OS Independent
Requires-Python: >=3.10
License-File: LICENSE.md
Requires-Dist: ray~=2.46.0
Requires-Dist: numpy~=2.2.6
Requires-Dist: xgboost~=3.0.4
Requires-Dist: pandas~=2.3.1
Requires-Dist: imbalanced-learn~=0.13.0
Requires-Dist: scikit-learn~=1.6.1
Requires-Dist: setuptools~=80.9.0
Requires-Dist: colorlog~=6.9.0
Requires-Dist: tqdm~=4.67.1
Dynamic: author
Dynamic: author-email
Dynamic: classifier
Dynamic: description
Dynamic: description-content-type
Dynamic: home-page
Dynamic: license
Dynamic: license-file
Dynamic: requires-dist
Dynamic: requires-python
Dynamic: summary
